jps_controlled_vocabularies_rest_api/__init__.py
jps_controlled_vocabularies_rest_api/config.py
jps_controlled_vocabularies_rest_api/deps.py
jps_controlled_vocabularies_rest_api/main.py
jps_controlled_vocabularies_rest_api/models/__init__.py
jps_controlled_vocabularies_rest_api/models/api_models.py
jps_controlled_vocabularies_rest_api/routers/__init__.py
jps_controlled_vocabularies_rest_api/routers/health.py
jps_controlled_vocabularies_rest_api/routers/search.py
jps_controlled_vocabularies_rest_api/routers/validate.py
jps_controlled_vocabularies_rest_api/routers/vocabularies.py
jps_controlled_vocabularies_rest_api/stores/__init__.py
jps_controlled_vocabularies_rest_api/stores/base.py
jps_controlled_vocabularies_rest_api/stores/yaml_store.py
jps_controlled_vocabularies_rest_api-0.1.0.dist-info/licenses/LICENSE
jps_controlled_vocabularies_rest_api-0.1.0.dist-info/METADATA
jps_controlled_vocabularies_rest_api-0.1.0.dist-info/WHEEL
jps_controlled_vocabularies_rest_api-0.1.0.dist-info/entry_points.txt
jps_controlled_vocabularies_rest_api-0.1.0.dist-info/top_level.txt
jps_controlled_vocabularies_rest_api-0.1.0.dist-info/RECORD
